[
    {
        "FilterGroup": 0,
        "FilterOperator": "<>",
        "FilterValue": "$Vlocity.NULL",
        "GlobalKey": "DRDuplicateDetectionCase4Customa3P0Q000002ke3CUAQItem0",
        "InputFieldName": "Birth_Name__pc",
        "InputObjectName": "Account",
        "InputObjectQuerySequence": 1,
        "IsDisabled": false,
        "IsRequiredForUpsert": false,
        "IsUpsertKey": false,
        "Name": "DRDuplicateDetectionCase4",
        "OmniDataTransformationId": {
            "Name": "DRDuplicateDetectionCase4",
            "VlocityDataPackType": "VlocityMatchingKeyObject",
            "VlocityMatchingRecordSourceKey": "OmniDataTransform/DRDuplicateDetectionCase4",
            "VlocityRecordSObjectType": "OmniDataTransform"
        },
        "OutputCreationSequence": 0,
        "OutputFieldName": "PersonAccount",
        "OutputObjectName": "json",
        "VlocityDataPackType": "SObject",
        "VlocityRecordSObjectType": "OmniDataTransformItem"
    },
    {
        "FilterGroup": 0,
        "FilterOperator": "~=",
        "FilterValue": "LastName",
        "GlobalKey": "DRDuplicateDetectionCase4Customa3P0Q000002ke3CUAQItem1",
        "InputFieldName": "Birth_Name__pc",
        "InputObjectName": "Account",
        "InputObjectQuerySequence": 1,
        "IsDisabled": false,
        "IsRequiredForUpsert": false,
        "IsUpsertKey": false,
        "Name": "DRDuplicateDetectionCase4",
        "OmniDataTransformationId": {
            "Name": "DRDuplicateDetectionCase4",
            "VlocityDataPackType": "VlocityMatchingKeyObject",
            "VlocityMatchingRecordSourceKey": "OmniDataTransform/DRDuplicateDetectionCase4",
            "VlocityRecordSObjectType": "OmniDataTransform"
        },
        "OutputCreationSequence": 0,
        "OutputFieldName": "PersonAccount",
        "OutputObjectName": "json",
        "VlocityDataPackType": "SObject",
        "VlocityRecordSObjectType": "OmniDataTransformItem"
    },
    {
        "FilterGroup": 0,
        "FilterOperator": "~=",
        "FilterValue": "FirstName",
        "GlobalKey": "DRDuplicateDetectionCase4Customa3P0Q000002ke3CUAQItem3",
        "InputFieldName": "FirstName",
        "InputObjectName": "Account",
        "InputObjectQuerySequence": 1,
        "IsDisabled": false,
        "IsRequiredForUpsert": false,
        "IsUpsertKey": false,
        "Name": "DRDuplicateDetectionCase4",
        "OmniDataTransformationId": {
            "Name": "DRDuplicateDetectionCase4",
            "VlocityDataPackType": "VlocityMatchingKeyObject",
            "VlocityMatchingRecordSourceKey": "OmniDataTransform/DRDuplicateDetectionCase4",
            "VlocityRecordSObjectType": "OmniDataTransform"
        },
        "OutputCreationSequence": 0,
        "OutputFieldName": "PersonAccount",
        "OutputObjectName": "json",
        "VlocityDataPackType": "SObject",
        "VlocityRecordSObjectType": "OmniDataTransformItem"
    },
    {
        "FilterGroup": 0,
        "FilterOperator": "=",
        "FilterValue": "BirthDate",
        "GlobalKey": "DRDuplicateDetectionCase4Customa3P0Q000002ke3CUAQItem2",
        "InputFieldName": "PersonBirthdate",
        "InputObjectName": "Account",
        "InputObjectQuerySequence": 1,
        "IsDisabled": false,
        "IsRequiredForUpsert": false,
        "IsUpsertKey": false,
        "Name": "DRDuplicateDetectionCase4",
        "OmniDataTransformationId": {
            "Name": "DRDuplicateDetectionCase4",
            "VlocityDataPackType": "VlocityMatchingKeyObject",
            "VlocityMatchingRecordSourceKey": "OmniDataTransform/DRDuplicateDetectionCase4",
            "VlocityRecordSObjectType": "OmniDataTransform"
        },
        "OutputCreationSequence": 0,
        "OutputFieldName": "PersonAccount",
        "OutputObjectName": "json",
        "VlocityDataPackType": "SObject",
        "VlocityRecordSObjectType": "OmniDataTransformItem"
    },
    {
        "FilterGroup": 1,
        "FilterOperator": "=",
        "FilterValue": "$Vlocity.NULL",
        "GlobalKey": "DRDuplicateDetectionCase4Customa3P0Q000002ke3CUAQItem4",
        "InputFieldName": "Birth_Name__pc",
        "InputObjectName": "Account",
        "InputObjectQuerySequence": 1,
        "IsDisabled": false,
        "IsRequiredForUpsert": false,
        "IsUpsertKey": false,
        "Name": "DRDuplicateDetectionCase4",
        "OmniDataTransformationId": {
            "Name": "DRDuplicateDetectionCase4",
            "VlocityDataPackType": "VlocityMatchingKeyObject",
            "VlocityMatchingRecordSourceKey": "OmniDataTransform/DRDuplicateDetectionCase4",
            "VlocityRecordSObjectType": "OmniDataTransform"
        },
        "OutputCreationSequence": 0,
        "OutputFieldName": "PersonAccount",
        "OutputObjectName": "json",
        "VlocityDataPackType": "SObject",
        "VlocityRecordSObjectType": "OmniDataTransformItem"
    },
    {
        "FilterGroup": 1,
        "FilterOperator": "~=",
        "FilterValue": "FirstName",
        "GlobalKey": "DRDuplicateDetectionCase4Customa3P0Q000002ke3CUAQItem6",
        "InputFieldName": "FirstName",
        "InputObjectName": "Account",
        "InputObjectQuerySequence": 1,
        "IsDisabled": false,
        "IsRequiredForUpsert": false,
        "IsUpsertKey": false,
        "Name": "DRDuplicateDetectionCase4",
        "OmniDataTransformationId": {
            "Name": "DRDuplicateDetectionCase4",
            "VlocityDataPackType": "VlocityMatchingKeyObject",
            "VlocityMatchingRecordSourceKey": "OmniDataTransform/DRDuplicateDetectionCase4",
            "VlocityRecordSObjectType": "OmniDataTransform"
        },
        "OutputCreationSequence": 0,
        "OutputFieldName": "PersonAccount",
        "OutputObjectName": "json",
        "VlocityDataPackType": "SObject",
        "VlocityRecordSObjectType": "OmniDataTransformItem"
    },
    {
        "FilterGroup": 1,
        "FilterOperator": "~=",
        "FilterValue": "LastName",
        "GlobalKey": "DRDuplicateDetectionCase4Customa3P0Q000002ke3CUAQItem7",
        "InputFieldName": "LastName",
        "InputObjectName": "Account",
        "InputObjectQuerySequence": 1,
        "IsDisabled": false,
        "IsRequiredForUpsert": false,
        "IsUpsertKey": false,
        "Name": "DRDuplicateDetectionCase4",
        "OmniDataTransformationId": {
            "Name": "DRDuplicateDetectionCase4",
            "VlocityDataPackType": "VlocityMatchingKeyObject",
            "VlocityMatchingRecordSourceKey": "OmniDataTransform/DRDuplicateDetectionCase4",
            "VlocityRecordSObjectType": "OmniDataTransform"
        },
        "OutputCreationSequence": 0,
        "OutputFieldName": "PersonAccount",
        "OutputObjectName": "json",
        "VlocityDataPackType": "SObject",
        "VlocityRecordSObjectType": "OmniDataTransformItem"
    },
    {
        "FilterGroup": 1,
        "FilterOperator": "=",
        "FilterValue": "BirthDate",
        "GlobalKey": "DRDuplicateDetectionCase4Customa3P0Q000002ke3CUAQItem5",
        "InputFieldName": "PersonBirthdate",
        "InputObjectName": "Account",
        "InputObjectQuerySequence": 1,
        "IsDisabled": false,
        "IsRequiredForUpsert": false,
        "IsUpsertKey": false,
        "Name": "DRDuplicateDetectionCase4",
        "OmniDataTransformationId": {
            "Name": "DRDuplicateDetectionCase4",
            "VlocityDataPackType": "VlocityMatchingKeyObject",
            "VlocityMatchingRecordSourceKey": "OmniDataTransform/DRDuplicateDetectionCase4",
            "VlocityRecordSObjectType": "OmniDataTransform"
        },
        "OutputCreationSequence": 0,
        "OutputFieldName": "PersonAccount",
        "OutputObjectName": "json",
        "VlocityDataPackType": "SObject",
        "VlocityRecordSObjectType": "OmniDataTransformItem"
    },
    {
        "FilterGroup": 0,
        "FilterOperator": "=",
        "FilterValue": "PersonAccount:Id",
        "GlobalKey": "DRDuplicateDetectionCase4Customa3P0Q000002ke3CUAQItem8",
        "InputFieldName": "NameInsuredId",
        "InputObjectName": "InsurancePolicy",
        "InputObjectQuerySequence": 2,
        "IsDisabled": false,
        "IsRequiredForUpsert": false,
        "IsUpsertKey": false,
        "Name": "DRDuplicateDetectionCase4",
        "OmniDataTransformationId": {
            "Name": "DRDuplicateDetectionCase4",
            "VlocityDataPackType": "VlocityMatchingKeyObject",
            "VlocityMatchingRecordSourceKey": "OmniDataTransform/DRDuplicateDetectionCase4",
            "VlocityRecordSObjectType": "OmniDataTransform"
        },
        "OutputCreationSequence": 0,
        "OutputFieldName": "PersonAccount:PolicyHolded",
        "OutputObjectName": "json",
        "VlocityDataPackType": "SObject",
        "VlocityRecordSObjectType": "OmniDataTransformItem"
    },
    {
        "FilterGroup": 0,
        "FilterOperator": "=",
        "FilterValue": "ProductSubType",
        "GlobalKey": "DRDuplicateDetectionCase4Customa3P0Q000002ke3CUAQItem9",
        "InputFieldName": "Product.%vlocity_namespace%__Type__c",
        "InputObjectName": "InsurancePolicy",
        "InputObjectQuerySequence": 2,
        "IsDisabled": false,
        "IsRequiredForUpsert": false,
        "IsUpsertKey": false,
        "Name": "DRDuplicateDetectionCase4",
        "OmniDataTransformationId": {
            "Name": "DRDuplicateDetectionCase4",
            "VlocityDataPackType": "VlocityMatchingKeyObject",
            "VlocityMatchingRecordSourceKey": "OmniDataTransform/DRDuplicateDetectionCase4",
            "VlocityRecordSObjectType": "OmniDataTransform"
        },
        "OutputCreationSequence": 0,
        "OutputFieldName": "PersonAccount:PolicyHolded",
        "OutputObjectName": "json",
        "VlocityDataPackType": "SObject",
        "VlocityRecordSObjectType": "OmniDataTransformItem"
    },
    {
        "FilterGroup": 0,
        "FilterOperator": "<>",
        "FilterValue": "'Canceled'",
        "GlobalKey": "DRDuplicateDetectionCase4Customa3P0Q000002ke3CUAQItem14",
        "InputFieldName": "Status",
        "InputObjectName": "InsurancePolicy",
        "InputObjectQuerySequence": 2,
        "IsDisabled": false,
        "IsRequiredForUpsert": false,
        "IsUpsertKey": false,
        "Name": "DRDuplicateDetectionCase4",
        "OmniDataTransformationId": {
            "Name": "DRDuplicateDetectionCase4",
            "VlocityDataPackType": "VlocityMatchingKeyObject",
            "VlocityMatchingRecordSourceKey": "OmniDataTransform/DRDuplicateDetectionCase4",
            "VlocityRecordSObjectType": "OmniDataTransform"
        },
        "OutputCreationSequence": 0,
        "OutputFieldName": "PersonAccount:PolicyHolded",
        "OutputObjectName": "json",
        "VlocityDataPackType": "SObject",
        "VlocityRecordSObjectType": "OmniDataTransformItem"
    },
    {
        "FilterGroup": 0,
        "FilterOperator": "<>",
        "FilterValue": "'Expired'",
        "GlobalKey": "DRDuplicateDetectionCase4Customa3P0Q000002ke3CUAQItem12",
        "InputFieldName": "Status",
        "InputObjectName": "InsurancePolicy",
        "InputObjectQuerySequence": 2,
        "IsDisabled": false,
        "IsRequiredForUpsert": false,
        "IsUpsertKey": false,
        "Name": "DRDuplicateDetectionCase4",
        "OmniDataTransformationId": {
            "Name": "DRDuplicateDetectionCase4",
            "VlocityDataPackType": "VlocityMatchingKeyObject",
            "VlocityMatchingRecordSourceKey": "OmniDataTransform/DRDuplicateDetectionCase4",
            "VlocityRecordSObjectType": "OmniDataTransform"
        },
        "OutputCreationSequence": 0,
        "OutputFieldName": "PersonAccount:PolicyHolded",
        "OutputObjectName": "json",
        "VlocityDataPackType": "SObject",
        "VlocityRecordSObjectType": "OmniDataTransformItem"
    },
    {
        "FilterGroup": 0,
        "FilterOperator": "<>",
        "FilterValue": "'Résilié'",
        "GlobalKey": "DRDuplicateDetectionCase4Customa3P0Q000002ke3CUAQItem15",
        "InputFieldName": "Status",
        "InputObjectName": "InsurancePolicy",
        "InputObjectQuerySequence": 2,
        "IsDisabled": false,
        "IsRequiredForUpsert": false,
        "IsUpsertKey": false,
        "Name": "DRDuplicateDetectionCase4",
        "OmniDataTransformationId": {
            "Name": "DRDuplicateDetectionCase4",
            "VlocityDataPackType": "VlocityMatchingKeyObject",
            "VlocityMatchingRecordSourceKey": "OmniDataTransform/DRDuplicateDetectionCase4",
            "VlocityRecordSObjectType": "OmniDataTransform"
        },
        "OutputCreationSequence": 0,
        "OutputFieldName": "PersonAccount:PolicyHolded",
        "OutputObjectName": "json",
        "VlocityDataPackType": "SObject",
        "VlocityRecordSObjectType": "OmniDataTransformItem"
    },
    {
        "FilterGroup": 0,
        "FilterOperator": "=",
        "FilterValue": "ProductSubType",
        "GlobalKey": "DRDuplicateDetectionCase4Customa3P0Q000002ke3CUAQItem10",
        "InputFieldName": "InsurancePolicy.Product.%vlocity_namespace%__Type__c",
        "InputObjectName": "InsurancePolicyParticipant",
        "InputObjectQuerySequence": 3,
        "IsDisabled": false,
        "IsRequiredForUpsert": false,
        "IsUpsertKey": false,
        "Name": "DRDuplicateDetectionCase4",
        "OmniDataTransformationId": {
            "Name": "DRDuplicateDetectionCase4",
            "VlocityDataPackType": "VlocityMatchingKeyObject",
            "VlocityMatchingRecordSourceKey": "OmniDataTransform/DRDuplicateDetectionCase4",
            "VlocityRecordSObjectType": "OmniDataTransform"
        },
        "OutputCreationSequence": 0,
        "OutputFieldName": "PersonAccount:PolicyParticiped",
        "OutputObjectName": "json",
        "VlocityDataPackType": "SObject",
        "VlocityRecordSObjectType": "OmniDataTransformItem"
    },
    {
        "FilterGroup": 0,
        "FilterOperator": "<>",
        "FilterValue": "'Canceled'",
        "GlobalKey": "DRDuplicateDetectionCase4Customa3P0Q000002ke3CUAQItem16",
        "InputFieldName": "InsurancePolicy.Status",
        "InputObjectName": "InsurancePolicyParticipant",
        "InputObjectQuerySequence": 3,
        "IsDisabled": false,
        "IsRequiredForUpsert": false,
        "IsUpsertKey": false,
        "Name": "DRDuplicateDetectionCase4",
        "OmniDataTransformationId": {
            "Name": "DRDuplicateDetectionCase4",
            "VlocityDataPackType": "VlocityMatchingKeyObject",
            "VlocityMatchingRecordSourceKey": "OmniDataTransform/DRDuplicateDetectionCase4",
            "VlocityRecordSObjectType": "OmniDataTransform"
        },
        "OutputCreationSequence": 0,
        "OutputFieldName": "PersonAccount:PolicyParticiped",
        "OutputObjectName": "json",
        "VlocityDataPackType": "SObject",
        "VlocityRecordSObjectType": "OmniDataTransformItem"
    },
    {
        "FilterGroup": 0,
        "FilterOperator": "<>",
        "FilterValue": "'Expired'",
        "GlobalKey": "DRDuplicateDetectionCase4Customa3P0Q000002ke3CUAQItem13",
        "InputFieldName": "InsurancePolicy.Status",
        "InputObjectName": "InsurancePolicyParticipant",
        "InputObjectQuerySequence": 3,
        "IsDisabled": false,
        "IsRequiredForUpsert": false,
        "IsUpsertKey": false,
        "Name": "DRDuplicateDetectionCase4",
        "OmniDataTransformationId": {
            "Name": "DRDuplicateDetectionCase4",
            "VlocityDataPackType": "VlocityMatchingKeyObject",
            "VlocityMatchingRecordSourceKey": "OmniDataTransform/DRDuplicateDetectionCase4",
            "VlocityRecordSObjectType": "OmniDataTransform"
        },
        "OutputCreationSequence": 0,
        "OutputFieldName": "PersonAccount:PolicyParticiped",
        "OutputObjectName": "json",
        "VlocityDataPackType": "SObject",
        "VlocityRecordSObjectType": "OmniDataTransformItem"
    },
    {
        "FilterGroup": 0,
        "FilterOperator": "<>",
        "FilterValue": "'Résilié'",
        "GlobalKey": "DRDuplicateDetectionCase4Customa3P0Q000002ke3CUAQItem17",
        "InputFieldName": "InsurancePolicy.Status",
        "InputObjectName": "InsurancePolicyParticipant",
        "InputObjectQuerySequence": 3,
        "IsDisabled": false,
        "IsRequiredForUpsert": false,
        "IsUpsertKey": false,
        "Name": "DRDuplicateDetectionCase4",
        "OmniDataTransformationId": {
            "Name": "DRDuplicateDetectionCase4",
            "VlocityDataPackType": "VlocityMatchingKeyObject",
            "VlocityMatchingRecordSourceKey": "OmniDataTransform/DRDuplicateDetectionCase4",
            "VlocityRecordSObjectType": "OmniDataTransform"
        },
        "OutputCreationSequence": 0,
        "OutputFieldName": "PersonAccount:PolicyParticiped",
        "OutputObjectName": "json",
        "VlocityDataPackType": "SObject",
        "VlocityRecordSObjectType": "OmniDataTransformItem"
    },
    {
        "FilterGroup": 0,
        "FilterOperator": "=",
        "FilterValue": "PersonAccount:Id",
        "GlobalKey": "DRDuplicateDetectionCase4Customa3P0Q000002ke3CUAQItem11",
        "InputFieldName": "PrimaryParticipantAccountId",
        "InputObjectName": "InsurancePolicyParticipant",
        "InputObjectQuerySequence": 3,
        "IsDisabled": false,
        "IsRequiredForUpsert": false,
        "IsUpsertKey": false,
        "Name": "DRDuplicateDetectionCase4",
        "OmniDataTransformationId": {
            "Name": "DRDuplicateDetectionCase4",
            "VlocityDataPackType": "VlocityMatchingKeyObject",
            "VlocityMatchingRecordSourceKey": "OmniDataTransform/DRDuplicateDetectionCase4",
            "VlocityRecordSObjectType": "OmniDataTransform"
        },
        "OutputCreationSequence": 0,
        "OutputFieldName": "PersonAccount:PolicyParticiped",
        "OutputObjectName": "json",
        "VlocityDataPackType": "SObject",
        "VlocityRecordSObjectType": "OmniDataTransformItem"
    },
    {
        "GlobalKey": "DRDuplicateDetectionCase4Customa3P0Q000002ke3CUAQItem54",
        "InputFieldName": "PersonAccount:Id",
        "IsDisabled": false,
        "IsRequiredForUpsert": false,
        "IsUpsertKey": false,
        "Name": "DRDuplicateDetectionCase4",
        "OmniDataTransformationId": {
            "Name": "DRDuplicateDetectionCase4",
            "VlocityDataPackType": "VlocityMatchingKeyObject",
            "VlocityMatchingRecordSourceKey": "OmniDataTransform/DRDuplicateDetectionCase4",
            "VlocityRecordSObjectType": "OmniDataTransform"
        },
        "OutputCreationSequence": 1,
        "OutputFieldName": "AccountID",
        "OutputObjectName": "json",
        "VlocityDataPackType": "SObject",
        "VlocityRecordSObjectType": "OmniDataTransformItem"
    },
    {
        "GlobalKey": "DRDuplicateDetectionCase4Customa3P0Q000002ke3CUAQItem76",
        "InputFieldName": "PersonAccount:Name",
        "IsDisabled": false,
        "IsRequiredForUpsert": false,
        "IsUpsertKey": false,
        "Name": "DRDuplicateDetectionCase4",
        "OmniDataTransformationId": {
            "Name": "DRDuplicateDetectionCase4",
            "VlocityDataPackType": "VlocityMatchingKeyObject",
            "VlocityMatchingRecordSourceKey": "OmniDataTransform/DRDuplicateDetectionCase4",
            "VlocityRecordSObjectType": "OmniDataTransform"
        },
        "OutputCreationSequence": 1,
        "OutputFieldName": "Name",
        "OutputObjectName": "json",
        "VlocityDataPackType": "SObject",
        "VlocityRecordSObjectType": "OmniDataTransformItem"
    },
    {
        "GlobalKey": "DRDuplicateDetectionCase4Custom7193",
        "InputFieldName": "PersonAccount:PolicyHolded:NameInsuredId",
        "IsDisabled": false,
        "IsRequiredForUpsert": false,
        "IsUpsertKey": false,
        "Name": "DRDuplicateDetectionCase4",
        "OmniDataTransformationId": {
            "Name": "DRDuplicateDetectionCase4",
            "VlocityDataPackType": "VlocityMatchingKeyObject",
            "VlocityMatchingRecordSourceKey": "OmniDataTransform/DRDuplicateDetectionCase4",
            "VlocityRecordSObjectType": "OmniDataTransform"
        },
        "OutputCreationSequence": 1,
        "OutputFieldName": "PoliciesHolded:AccountId",
        "OutputObjectName": "json",
        "VlocityDataPackType": "SObject",
        "VlocityRecordSObjectType": "OmniDataTransformItem"
    },
    {
        "GlobalKey": "DRDuplicateDetectionCase4Customa3P0Q000002ke3CUAQItem78",
        "InputFieldName": "PersonAccount:PolicyHolded:Product.%vlocity_namespace%__Type__c",
        "IsDisabled": false,
        "IsRequiredForUpsert": false,
        "IsUpsertKey": false,
        "Name": "DRDuplicateDetectionCase4",
        "OmniDataTransformationId": {
            "Name": "DRDuplicateDetectionCase4",
            "VlocityDataPackType": "VlocityMatchingKeyObject",
            "VlocityMatchingRecordSourceKey": "OmniDataTransform/DRDuplicateDetectionCase4",
            "VlocityRecordSObjectType": "OmniDataTransform"
        },
        "OutputCreationSequence": 1,
        "OutputFieldName": "PoliciesHolded:Family",
        "OutputObjectName": "json",
        "VlocityDataPackType": "SObject",
        "VlocityRecordSObjectType": "OmniDataTransformItem"
    },
    {
        "GlobalKey": "DRDuplicateDetectionCase4Customa3P0Q000002ke3CUAQItem77",
        "InputFieldName": "PersonAccount:PolicyHolded:Name",
        "IsDisabled": false,
        "IsRequiredForUpsert": false,
        "IsUpsertKey": false,
        "Name": "DRDuplicateDetectionCase4",
        "OmniDataTransformationId": {
            "Name": "DRDuplicateDetectionCase4",
            "VlocityDataPackType": "VlocityMatchingKeyObject",
            "VlocityMatchingRecordSourceKey": "OmniDataTransform/DRDuplicateDetectionCase4",
            "VlocityRecordSObjectType": "OmniDataTransform"
        },
        "OutputCreationSequence": 1,
        "OutputFieldName": "PoliciesHolded:Name",
        "OutputObjectName": "json",
        "VlocityDataPackType": "SObject",
        "VlocityRecordSObjectType": "OmniDataTransformItem"
    },
    {
        "GlobalKey": "DRDuplicateDetectionCase4Customa3P0Q000002ke3CUAQItem75",
        "InputFieldName": "PersonAccount:PolicyHolded:Id",
        "IsDisabled": false,
        "IsRequiredForUpsert": false,
        "IsUpsertKey": false,
        "Name": "DRDuplicateDetectionCase4",
        "OmniDataTransformationId": {
            "Name": "DRDuplicateDetectionCase4",
            "VlocityDataPackType": "VlocityMatchingKeyObject",
            "VlocityMatchingRecordSourceKey": "OmniDataTransform/DRDuplicateDetectionCase4",
            "VlocityRecordSObjectType": "OmniDataTransform"
        },
        "OutputCreationSequence": 1,
        "OutputFieldName": "PoliciesHolded:PolicyId",
        "OutputObjectName": "json",
        "VlocityDataPackType": "SObject",
        "VlocityRecordSObjectType": "OmniDataTransformItem"
    },
    {
        "GlobalKey": "DRDuplicateDetectionCase4Customa3P0Q000002ke3CUAQItem79",
        "InputFieldName": "PersonAccount:PolicyHolded:Status",
        "IsDisabled": false,
        "IsRequiredForUpsert": false,
        "IsUpsertKey": false,
        "Name": "DRDuplicateDetectionCase4",
        "OmniDataTransformationId": {
            "Name": "DRDuplicateDetectionCase4",
            "VlocityDataPackType": "VlocityMatchingKeyObject",
            "VlocityMatchingRecordSourceKey": "OmniDataTransform/DRDuplicateDetectionCase4",
            "VlocityRecordSObjectType": "OmniDataTransform"
        },
        "OutputCreationSequence": 1,
        "OutputFieldName": "PoliciesHolded:Status",
        "OutputObjectName": "json",
        "VlocityDataPackType": "SObject",
        "VlocityRecordSObjectType": "OmniDataTransformItem"
    },
    {
        "GlobalKey": "DRDuplicateDetectionCase4Custom4467",
        "InputFieldName": "PersonAccount:PolicyParticiped:InsurancePolicy.NameInsuredId",
        "IsDisabled": false,
        "IsRequiredForUpsert": false,
        "IsUpsertKey": false,
        "Name": "DRDuplicateDetectionCase4",
        "OmniDataTransformationId": {
            "Name": "DRDuplicateDetectionCase4",
            "VlocityDataPackType": "VlocityMatchingKeyObject",
            "VlocityMatchingRecordSourceKey": "OmniDataTransform/DRDuplicateDetectionCase4",
            "VlocityRecordSObjectType": "OmniDataTransform"
        },
        "OutputCreationSequence": 1,
        "OutputFieldName": "PolicyParticiped:AccountId",
        "OutputObjectName": "json",
        "VlocityDataPackType": "SObject",
        "VlocityRecordSObjectType": "OmniDataTransformItem"
    },
    {
        "GlobalKey": "DRDuplicateDetectionCase4Customa3P0Q000002ke3CUAQItem71",
        "InputFieldName": "PersonAccount:PolicyParticiped:InsurancePolicy.Product.%vlocity_namespace%__Type__c",
        "IsDisabled": false,
        "IsRequiredForUpsert": false,
        "IsUpsertKey": false,
        "Name": "DRDuplicateDetectionCase4",
        "OmniDataTransformationId": {
            "Name": "DRDuplicateDetectionCase4",
            "VlocityDataPackType": "VlocityMatchingKeyObject",
            "VlocityMatchingRecordSourceKey": "OmniDataTransform/DRDuplicateDetectionCase4",
            "VlocityRecordSObjectType": "OmniDataTransform"
        },
        "OutputCreationSequence": 1,
        "OutputFieldName": "PolicyParticiped:Family",
        "OutputObjectName": "json",
        "VlocityDataPackType": "SObject",
        "VlocityRecordSObjectType": "OmniDataTransformItem"
    },
    {
        "GlobalKey": "DRDuplicateDetectionCase4Customa3P0Q000002ke3CUAQItem83",
        "InputFieldName": "PersonAccount:PolicyParticiped:InsurancePolicy.Name",
        "IsDisabled": false,
        "IsRequiredForUpsert": false,
        "IsUpsertKey": false,
        "Name": "DRDuplicateDetectionCase4",
        "OmniDataTransformationId": {
            "Name": "DRDuplicateDetectionCase4",
            "VlocityDataPackType": "VlocityMatchingKeyObject",
            "VlocityMatchingRecordSourceKey": "OmniDataTransform/DRDuplicateDetectionCase4",
            "VlocityRecordSObjectType": "OmniDataTransform"
        },
        "OutputCreationSequence": 1,
        "OutputFieldName": "PolicyParticiped:Name",
        "OutputObjectName": "json",
        "VlocityDataPackType": "SObject",
        "VlocityRecordSObjectType": "OmniDataTransformItem"
    },
    {
        "GlobalKey": "DRDuplicateDetectionCase4Customa3P0Q000002ke3CUAQItem82",
        "InputFieldName": "PersonAccount:PolicyParticiped:InsurancePolicyId",
        "IsDisabled": false,
        "IsRequiredForUpsert": false,
        "IsUpsertKey": false,
        "Name": "DRDuplicateDetectionCase4",
        "OmniDataTransformationId": {
            "Name": "DRDuplicateDetectionCase4",
            "VlocityDataPackType": "VlocityMatchingKeyObject",
            "VlocityMatchingRecordSourceKey": "OmniDataTransform/DRDuplicateDetectionCase4",
            "VlocityRecordSObjectType": "OmniDataTransform"
        },
        "OutputCreationSequence": 1,
        "OutputFieldName": "PolicyParticiped:PolicyId",
        "OutputObjectName": "json",
        "VlocityDataPackType": "SObject",
        "VlocityRecordSObjectType": "OmniDataTransformItem"
    },
    {
        "GlobalKey": "DRDuplicateDetectionCase4Customa3P0Q000002ke3CUAQItem80",
        "InputFieldName": "PersonAccount:PolicyParticiped:InsurancePolicy.Status",
        "IsDisabled": false,
        "IsRequiredForUpsert": false,
        "IsUpsertKey": false,
        "Name": "DRDuplicateDetectionCase4",
        "OmniDataTransformationId": {
            "Name": "DRDuplicateDetectionCase4",
            "VlocityDataPackType": "VlocityMatchingKeyObject",
            "VlocityMatchingRecordSourceKey": "OmniDataTransform/DRDuplicateDetectionCase4",
            "VlocityRecordSObjectType": "OmniDataTransform"
        },
        "OutputCreationSequence": 1,
        "OutputFieldName": "PolicyParticiped:Status",
        "OutputObjectName": "json",
        "VlocityDataPackType": "SObject",
        "VlocityRecordSObjectType": "OmniDataTransformItem"
    }
]